statdb/__init__.py
statdb-0.0.0.dist-info/METADATA
statdb-0.0.0.dist-info/WHEEL
statdb-0.0.0.dist-info/top_level.txt
statdb-0.0.0.dist-info/RECORD
