Metadata-Version: 2.1
Name: statdb
Version: 0.0.0
Summary: Coming soon
Author-email: Your Name <you@example.com>
